[
  {
    "UUID": "301abb65-510e-44cb-9dd0-95383e8853c5",
    "bergabung": "04-10-2025_21-57-04",
    "username": "admin",
    "password": "jbsadmin17",
    "usernameHASH": "8c6976e5b5410415bde908bd4dee15dfb167a9c873fc4bb8a81f6f2ab448a918",
    "passwordHASH": "fd7bc9fc3f6bf1b2f7b511bd82fd2b03cfe10bd4863ebaa5e978245fd9d76a16",
    "name": "admin",
    "imageTemp": [],
    "videoTemp": [],
    "image": [],
    "video": [],
    "komentar": [],
    "suka": [],
    "simpan": [],
    "bagi": [],
    "ikuti": [],
    "diikuti": [],
    "settings": {},
    "arsip": [],
    "bio": "Aku admin",
    "laporkan": [],
    "kelamin": "L",
    "tempattanggallahir": "",
    "pp": "upload/pp/301abb65-510e-44cb-9dd0-95383e8853c5.jpg",
    "log": [],
    "email": "",
    "telp": "",
    "sembunyikansuka": true,
    "sembunyikanikuti": true,
    "sembunyikandiikuti": true,
    "profilprivat": true,
    "daftarblokir": [],
    "index": 0
  }
]
